JoyCat.py
JoyCat-0.0.11.dist-info/METADATA
JoyCat-0.0.11.dist-info/WHEEL
JoyCat-0.0.11.dist-info/entry_points.txt
JoyCat-0.0.11.dist-info/top_level.txt
JoyCat-0.0.11.dist-info/RECORD
