Metadata-Version: 2.1
Name: JoyCat
Version: 0.0.11
Summary: This package visualizes the happiness of cats based on Japanese traditional lore.
Home-page: https://github.com/yuta08/JoyCat
Author: yuta ishii
Author-email: s2022052@stu.musashino-u.ac.jp
License: UNKNOWN
Project-URL: Bug Tracker, https://github.com/yuta08/JoyCat
Platform: UNKNOWN
Classifier: Programming Language :: Python :: 3
Classifier: License :: OSI Approved :: MIT License
Classifier: Operating System :: OS Independent
Requires-Python: >=3.7
